Workbook

Sheet Sheet1
A1: QUESTION-1
A2: Item | B2: Quantity | C2: Rate | D2: Total Amount
A3: Mouse | B3: 12 | C3: 255 | D3: =B3 *C3 -> 3060
A4: KeyBoard | B4: 15 | C4: 340 | D4: =B4 *C4 -> 5100
A5: LED Moniter | B5: 9 | C5: 6200 | D5: =B5 *C5 -> 55800
A7: Q1. USE RELATIVE REFERENCING

Sheet Sheet2
A1: QUESTION-2
A2: Discount Percentage | E2: 0.05
A4: Item | B4: Quantity | C4: Rate | D4: amount | E4: Discount | F4: Total Amount
A5: Mouse | B5: 12 | C5: 255 | D5: =B5*C5 -> 3060 | E5: =D5*$E$2 -> 153 | F5: =B5*E5 -> 1836
A6: KeyBoard | B6: 15 | C6: 340 | D6: =B6*C6 -> 5100 | E6: =D6*$E$2 -> 255 | F6: =B6*E6 -> 3825
A7: LED Moniter | B7: 9 | C7: 6200 | D7: =B7*C7 -> 55800 | E7: =D7*$E$2 -> 2790 | F7: =B7*E7 -> 25110
A9: QUES- USE ABSOLUTE REFERENCING

Sheet Sheet3
A1: QUESTION-3
B2: Axis | C2: ICICI | D2: Bandhan | E2: SBI | F2: HDFC
A3: Loan Amount | B3: 0.12 | C3: 0.13 | D3: 0.125 | E3: 0.105 | F3: 0.14
A4: 2374500 | B4: =$A4*B$3 -> 284940 | C4: =$A4*C$3 -> 308685 | D4: =$A4*D$3 -> 296812.5 | E4: =$A4*E$3 -> 249322.5 | F4: =$A4*F$3 -> 332430
A5: 754500 | B5: =$A5*B$3 -> 90540 | C5: =$A5*C$3 -> 98085 | D5: =$A5*D$3 -> 94312.5 | E5: =$A5*E$3 -> 79222.5 | F5: =$A5*F$3 -> 105630
A6: 3497000 | B6: =$A6*B$3 -> 419640 | C6: =$A6*C$3 -> 454610 | D6: =$A6*D$3 -> 437125 | E6: =$A6*E$3 -> 367185 | F6: =$A6*F$3 -> 489580
A7: 2515000 | B7: =$A7*B$3 -> 301800 | C7: =$A7*C$3 -> 326950 | D7: =$A7*D$3 -> 314375 | E7: =$A7*E$3 -> 264075 | F7: =$A7*F$3 -> 352100
A8: 4715500 | B8: =$A8*B$3 -> 565860 | C8: =$A8*C$3 -> 613015 | D8: =$A8*D$3 -> 589437.5 | E8: =$A8*E$3 -> 495127.5 | F8: =$A8*F$3 -> 660170
A9: 233000 | B9: =$A9*B$3 -> 27960 | C9: =$A9*C$3 -> 30290 | D9: =$A9*D$3 -> 29125 | E9: =$A9*E$3 -> 24465 | F9: =$A9*F$3 -> 32620
A10: 2751500 | B10: =$A10*B$3 -> 330180 | C10: =$A10*C$3 -> 357695 | D10: =$A10*D$3 -> 343937.5 | E10: =$A10*E$3 -> 288907.5 | F10: =$A10*F$3 -> 385210
A11: 1629000 | B11: =$A11*B$3 -> 195480 | C11: =$A11*C$3 -> 211770 | D11: =$A11*D$3 -> 203625 | E11: =$A11*E$3 -> 171045 | F11: =$A11*F$3 -> 228060
A12: 2157500 | B12: =$A12*B$3 -> 258900 | C12: =$A12*C$3 -> 280475 | D12: =$A12*D$3 -> 269687.5 | E12: =$A12*E$3 -> 226537.5 | F12: =$A12*F$3 -> 302050
A13: 3806000 | B13: =$A13*B$3 -> 456720 | C13: =$A13*C$3 -> 494780 | D13: =$A13*D$3 -> 475750 | E13: =$A13*E$3 -> 399630 | F13: =$A13*F$3 -> 532840
A14: 570500 | B14: =$A14*B$3 -> 68460 | C14: =$A14*C$3 -> 74165 | D14: =$A14*D$3 -> 71312.5 | E14: =$A14*E$3 -> 59902.5 | F14: =$A14*F$3 -> 79870
A15: 2397000 | B15: =$A15*B$3 -> 287640 | C15: =$A15*C$3 -> 311610 | D15: =$A15*D$3 -> 299625 | E15: =$A15*E$3 -> 251685 | F15: =$A15*F$3 -> 335580
... A20: 1184000 | B20: =$A20*B$3 -> 142080 | C20: =$A20*C$3 -> 153920 | D20: =$A20*D$3 -> 148000 | E20: =$A20*E$3 -> 124320 | F20: =$A20*F$3 -> 165760
A22: QUES- USE MIXED REFERENCING

Sheet Sheet4
A1: QUESTION-4 | F1: QUES- USE SHEET REFERENCING
A2: NORTH
A3: Item | B3: Q-1 | C3: Q-2 | D3: Q-3 | E3: Q-4
A4: Mouse | B4: =NORTH!B3 -> 44 | C4: =NORTH!C3 -> 37 | D4: =NORTH!D3 -> 35 | E4: =NORTH!E3 -> 37
A5: KeyBoard | B5: =NORTH!B4 -> 8 | C5: =NORTH!C4 -> 17 | D5: =NORTH!D4 -> 24 | E5: =NORTH!E4 -> 55
A6: LED Moniter | B6: =NORTH!B5 -> 45 | C6: =NORTH!C5 -> 40 | D6: =NORTH!D5 -> 32 | E6: =NORTH!E5 -> 37
A8: EAST
A9: Item | B9: Q-1 | C9: Q-2 | D9: Q-3 | E9: Q-4
A10: Mouse | B10: =EAST!B3 -> 95 | C10: =EAST!C3 -> 26 | D10: =EAST!D3 -> 78 | E10: =EAST!E3 -> 13
A11: KeyBoard | B11: =EAST!B4 -> 49 | C11: =EAST!C4 -> 81 | D11: =EAST!D4 -> 44 | E11: =EAST!E4 -> 97
A12: LED Moniter | B12: =EAST!B5 -> 51 | C12: =EAST!C5 -> 45 | D12: =EAST!D5 -> 79 | E12: =EAST!E5 -> 80
A14: SOUTH
A15: Item | B15: Q-1 | C15: Q-2 | D15: Q-3 | E15: Q-4
A16: Mouse | B16: =SOUTH!B3 -> 53 | C16: =SOUTH!C3 -> 40 | D16: =SOUTH!D3 -> 71 | E16: =SOUTH!E3 -> 26
A17: KeyBoard | B17: =SOUTH!B4 -> 13 | C17: =SOUTH!C4 -> 68 | D17: =SOUTH!D4 -> 75 | E17: =SOUTH!E4 -> 62
A18: LED Moniter | B18: =SOUTH!B5 -> 51 | C18: =SOUTH!C5 -> 57 | D18: =SOUTH!D5 -> 30 | E18: =SOUTH!E5 -> 40
A20: WEST
A21: Item | B21: Q-1 | C21: Q-2 | D21: Q-3 | E21: Q-4
A22: Mouse | B22: =WEST!B3 -> 55 | C22: =WEST!C3 -> 40 | D22: =WEST!D3 -> 51 | E22: =WEST!E3 -> 21
A23: KeyBoard | B23: =WEST!B4 -> 47 | C23: =WEST!C4 -> 62 | D23: =WEST!D4 -> 42 | E23: =WEST!E4 -> 43
A24: LED Moniter | B24: =WEST!B5 -> 72 | C24: =WEST!C5 -> 81 | D24: =WEST!D5 -> 87 | E24: =WEST!E5 -> 62

Sheet EAST
A1: QUESTION-4
A2: Item | B2: Q-1 | C2: Q-2 | D2: Q-3 | E2: Q-4
A3: Mouse | B3: 95 | C3: 26 | D3: 78 | E3: 13
A4: KeyBoard | B4: 49 | C4: 81 | D4: 44 | E4: 97
A5: LED Moniter | B5: 51 | C5: 45 | D5: 79 | E5: 80

Sheet SOUTH
A1: QUESTION-4
A2: Item | B2: Q-1 | C2: Q-2 | D2: Q-3 | E2: Q-4
A3: Mouse | B3: 53 | C3: 40 | D3: 71 | E3: 26
A4: KeyBoard | B4: 13 | C4: 68 | D4: 75 | E4: 62
A5: LED Moniter | B5: 51 | C5: 57 | D5: 30 | E5: 40

Sheet WEST
A1: QUESTION-4
A2: Item | B2: Q-1 | C2: Q-2 | D2: Q-3 | E2: Q-4
A3: Mouse | B3: 55 | C3: 40 | D3: 51 | E3: 21
A4: KeyBoard | B4: 47 | C4: 62 | D4: 42 | E4: 43
A5: LED Moniter | B5: 72 | C5: 81 | D5: 87 | E5: 62

Sheet NORTH
A1: QUESTION-4
A2: Item | B2: Q-1 | C2: Q-2 | D2: Q-3 | E2: Q-4
A3: Mouse | B3: 44 | C3: 37 | D3: 35 | E3: 37
A4: KeyBoard | B4: 8 | C4: 17 | D4: 24 | E4: 55
A5: LED Moniter | B5: 45 | C5: 40 | D5: 32 | E5: 37

Sheet Sheet9
A1: QUESTION-5
A2: Salesman | B2: Jan | C2: Feb | D2: Mar | E2: Total
A3: Amit | B3: 5600 | C3: 4500 | D3: 6540 | E3: =SUM(B3,C3,D3) -> 16640
A4: Ravi | B4: 8500 | C4: 6650 | D4: 6554 | E4: =SUM(B4,C4,D4) -> 21704
A5: Sanjay | B5: 9500 | C5: 4556 | D5: 12000 | E5: =SUM(B5,C5,D5) -> 26056
A6: Bikash | B6: 6900 | C6: 6850 | D6: 1200 | E6: =SUM(B6,C6,D6) -> 14950
A7: Rajesh | B7: 4500 | C7: 4585 | D7: 8020 | E7: =SUM(B7,C7,D7) -> 17105

Sheet Sheet10
A1: QUESTION-6
D2: 0.18
A3: Product | B3: Qty | C3: Rate | D3: GST@18%
A4: X | B4: 12 | C4: 450 | D4: =(B4*C4)*$D$2 -> 972
A5: Y | B5: 8 | C5: 340 | D5: =(B5*C5)*$D$2 -> 489.6
A6: Z | B6: 15 | C6: 280 | D6: =(B6*C6)*$D$2 -> 756

Sheet Sheet11
A1: QUESTION-7
A2: Basic | B2: KOLKATA | C2: MUMBAI | D2: DELHI
A3: SALARY | B3: 0.7 | C3: 0.6 | D3: 0.75
A4: 20000 | B4: =$A4*B$3 -> 14000 | C4: =$A4*C$3 -> 12000 | D4: =$A4*D$3 -> 15000
A5: 30000 | B5: =$A5*B$3 -> 21000 | C5: =$A5*C$3 -> 18000 | D5: =$A5*D$3 -> 22500
A6: 15000 | B6: =$A6*B$3 -> 10500 | C6: =$A6*C$3 -> 9000 | D6: =$A6*D$3 -> 11250
A7: 25000 | B7: =$A7*B$3 -> 17500 | C7: =$A7*C$3 -> 15000 | D7: =$A7*D$3 -> 18750

Sheet Sheet12
A1: QUESTION-8
A2: City Wise HRA Calculation
B3: 0.25 | C3: 0.3 | D3: 0.35
A4: Basic | B4: Kolkata | C4: Delhi | D4: Mumbai
A5: 5000 | B5: =$A5*B$3 -> 1250 | C5: =$A5*C$3 -> 1500 | D5: =$A5*D$3 -> 1750
A6: 10000 | B6: =$A6*B$3 -> 2500 | C6: =$A6*C$3 -> 3000 | D6: =$A6*D$3 -> 3500
A7: 15000 | B7: =$A7*B$3 -> 3750 | C7: =$A7*C$3 -> 4500 | D7: =$A7*D$3 -> 5250
A8: 20000 | B8: =$A8*B$3 -> 5000 | C8: =$A8*C$3 -> 6000 | D8: =$A8*D$3 -> 7000

Sheet Sheet13
A1: QUESTION-9
A2: Rate | B2: Loan amount
B3: 10000 | C3: 20000 | D3: 30000 | E3: 40000
A4: 0.05
A5: 0.055
A6: 0.06
A7: 0.065
A8: 0.07

Sheet Sheet14
A1: QUESTION-10
A2: code | B2: name | C2: basic | D2: 0.1 | E2: 0.07 | F2: 0.12 | G2: total
D3: DA | E3: TA | F3: HRA
A4: 555 | B4: ajay roy | C4: 5400 | D4: =$C4*D$2 -> 540 | E4: =$C4*E$2 -> 378 | F4: =$C4*F$2 -> 648 | G4: =SUM(C4,D4,E4,F4) -> 6966
A5: 232 | B5: vijay | C5: 2500 | D5: =$C5*D$2 -> 250 | E5: =$C5*E$2 -> 175 | F5: =$C5*F$2 -> 300 | G5: =SUM(C5,D5,E5,F5) -> 3225
A6: 845 | B6: neel sharma | C6: 4600 | D6: =$C6*D$2 -> 460 | E6: =$C6*E$2 -> 322 | F6: =$C6*F$2 -> 552 | G6: =SUM(C6,D6,E6,F6) -> 5934
A7: 888 | B7: sunil todi | C7: 3500 | D7: =$C7*D$2 -> 350 | E7: =$C7*E$2 -> 245 | F7: =$C7*F$2 -> 420 | G7: =SUM(C7,D7,E7,F7) -> 4515

Sheet Sheet15
A1: QUESTION-11
A2: COMMISSION(%) | B2: 0.005 | C2: 0.0075 | D2: 0.01 | E2: 0.0125 | F2: 0.015 | G2: 0.02
A3: EMPLOYEES | B3: REVENUE GENERATED
B4: JANUARY | C4: FEBRUARY | D4: MARCH | E4: APRIL | F4: MAY | G4: JUNE
A5: RAJ | B5: 15000 | C5: 13000 | D5: 13000 | E5: 36000 | F5: 32000 | G5: 50000
A6: MANOJ | B6: 15500 | C6: 32000 | D6: 23000 | E6: 37000 | F6: 48000 | G6: 47000
A7: IMRAN | B7: 12000 | C7: 14000 | D7: 31000 | E7: 13000 | F7: 32000 | G7: 43000
A8: ANKIT | B8: 14000 | C8: 34000 | D8: 26000 | E8: 16000 | F8: 14000 | G8: 28000
A9: PARTHA | B9: 24000 | C9: 18000 | D9: 42000 | E9: 10000 | F9: 7000 | G9: 29000
A10: TAPAS | B10: 32000 | C10: 19000 | D10: 16000 | E10: 16000 | F10: 92000 | G10: 54000
A12: EMPLOYEES
B13: JANUARY | C13: FEBRUARY | D13: MARCH | E13: APRIL | F13: MAY | G13: JUNE
A14: RAJ | B14: =B5*B$2 -> 75 | C14: =C5*C$2 -> 97.5 | D14: =D5*D$2 -> 130 | E14: =E5*E$2 -> 450 | F14: =F5*F$2 -> 480 | G14: =G5*G$2 -> 1000
A15: MANOJ | B15: =B6*B$2 -> 77.5 | C15: =C6*C$2 -> 240 | D15: =D6*D$2 -> 230 | E15: =E6*E$2 -> 462.5 | F15: =F6*F$2 -> 720 | G15: =G6*G$2 -> 940
A16: IMRAN | B16: =B7*B$2 -> 60 | C16: =C7*C$2 -> 105 | D16: =D7*D$2 -> 310 | E16: =E7*E$2 -> 162.5 | F16: =F7*F$2 -> 480 | G16: =G7*G$2 -> 860
A17: ANKIT | B17: =B8*B$2 -> 70 | C17: =C8*C$2 -> 255 | D17: =D8*D$2 -> 260 | E17: =E8*E$2 -> 200 | F17: =F8*F$2 -> 210 | G17: =G8*G$2 -> 560
A18: PARTHA | B18: =B9*B$2 -> 120 | C18: =C9*C$2 -> 135 | D18: =D9*D$2 -> 420 | E18: =E9*E$2 -> 125 | F18: =F9*F$2 -> 105 | G18: =G9*G$2 -> 580
A19: TAPAS | B19: =B10*B$2 -> 160 | C19: =C10*C$2 -> 142.5 | D19: =D10*D$2 -> 160 | E19: =E10*E$2 -> 200 | F19: =F10*F$2 -> 1380 | G19: =G10*G$2 -> 1080
A21: Calculate incentive of each month of every employee with the help of mixed cell reference
